Mysql51Cankaoshouce/README.md
Mysql51Cankaoshouce/__init__.py
Mysql51Cankaoshouce/__main__.py
Mysql51Cankaoshouce/file.epub
Mysql51Cankaoshouce/index.html
Mysql51Cankaoshouce/css/__init__.py
Mysql51Cankaoshouce/css/annotations.css
Mysql51Cankaoshouce/css/main.css
Mysql51Cankaoshouce/css/normalize.css
Mysql51Cankaoshouce/css/popup.css
Mysql51Cankaoshouce/font/__init__.py
Mysql51Cankaoshouce/font/fontello.eot
Mysql51Cankaoshouce/font/fontello.svg
Mysql51Cankaoshouce/font/fontello.ttf
Mysql51Cankaoshouce/font/fontello.woff
Mysql51Cankaoshouce/img/__init__.py
Mysql51Cankaoshouce/img/annotator-glyph-sprite.png
Mysql51Cankaoshouce/img/annotator-icon-sprite.png
Mysql51Cankaoshouce/img/apple-touch-icon.png
Mysql51Cankaoshouce/img/cancelfullscreen.png
Mysql51Cankaoshouce/img/close.png
Mysql51Cankaoshouce/img/fullscreen.png
Mysql51Cankaoshouce/img/loader.gif
Mysql51Cankaoshouce/img/menu-icon.png
Mysql51Cankaoshouce/img/save.png
Mysql51Cankaoshouce/img/saved.png
Mysql51Cankaoshouce/img/settings-s.png
Mysql51Cankaoshouce/img/settings.png
Mysql51Cankaoshouce/img/star.png
Mysql51Cankaoshouce/js/__init__.py
Mysql51Cankaoshouce/js/epub.js
Mysql51Cankaoshouce/js/epub.min.js
Mysql51Cankaoshouce/js/epub.min.map
Mysql51Cankaoshouce/js/hooks.min.js
Mysql51Cankaoshouce/js/hooks.min.map
Mysql51Cankaoshouce/js/reader.js
Mysql51Cankaoshouce/js/reader.js.map
Mysql51Cankaoshouce/js/reader.min.js
Mysql51Cankaoshouce/js/reader.min.map
Mysql51Cankaoshouce/js/hooks/__init__.py
Mysql51Cankaoshouce/js/hooks/extensions/__init__.py
Mysql51Cankaoshouce/js/hooks/extensions/highlight.js
Mysql51Cankaoshouce/js/libs/__init__.py
Mysql51Cankaoshouce/js/libs/jquery.min.js
Mysql51Cankaoshouce/js/libs/localforage.min.js
Mysql51Cankaoshouce/js/libs/screenfull.js
Mysql51Cankaoshouce/js/libs/screenfull.min.js
Mysql51Cankaoshouce/js/libs/zip.min.js
Mysql51Cankaoshouce/js/plugins/__init__.py
Mysql51Cankaoshouce/js/plugins/hypothesis.js
Mysql51Cankaoshouce/js/plugins/search.js
mysql5_1_cankaoshouce-2024.3.2.0.dist-info/METADATA
mysql5_1_cankaoshouce-2024.3.2.0.dist-info/WHEEL
mysql5_1_cankaoshouce-2024.3.2.0.dist-info/entry_points.txt
mysql5_1_cankaoshouce-2024.3.2.0.dist-info/top_level.txt
mysql5_1_cankaoshouce-2024.3.2.0.dist-info/RECORD
